capture_stdout_decorator/LICENSE
capture_stdout_decorator/README.MD
capture_stdout_decorator/__init__.py
capture_stdout_decorator/requirements.txt
capture_stdout_decorator/thirdparty.json
capture_stdout_decorator-0.10.dist-info/LICENSE.rst
capture_stdout_decorator-0.10.dist-info/METADATA
capture_stdout_decorator-0.10.dist-info/WHEEL
capture_stdout_decorator-0.10.dist-info/top_level.txt
capture_stdout_decorator-0.10.dist-info/RECORD
